spetlr/__init__.py
spetlr/alias.py
spetlr/db_auto.py
spetlr/functions.py
spetlr/spark.py
spetlr/transformations.py
spetlr/version.py
spetlr/azure_log_analytics/__init__.py
spetlr/azure_log_analytics/azure_log_analytics_handle.py
spetlr/cache/CachedLoader.py
spetlr/cache/CachedLoaderParameters.py
spetlr/cache/__init__.py
spetlr/config_master/__init__.py
spetlr/configurator/__init__.py
spetlr/configurator/configurator.py
spetlr/configurator/_cli/ConfiguratorCli.py
spetlr/configurator/_cli/__init__.py
spetlr/configurator/_cli/generate_keys_file.py
spetlr/configurator/sql/StatementBlocks.py
spetlr/configurator/sql/__init__.py
spetlr/configurator/sql/comments.py
spetlr/configurator/sql/create.py
spetlr/configurator/sql/db.py
spetlr/configurator/sql/exceptions.py
spetlr/configurator/sql/init_sqlparse.py
spetlr/configurator/sql/parse_sql.py
spetlr/configurator/sql/substructures.py
spetlr/configurator/sql/table.py
spetlr/configurator/sql/types.py
spetlr/configurator/sql/utils.py
spetlr/configurator/sql/view.py
spetlr/cosmos/__init__.py
spetlr/cosmos/cosmos.py
spetlr/cosmos/cosmos_base_server.py
spetlr/cosmos/cosmos_handle.py
spetlr/delta/__init__.py
spetlr/delta/db_handle.py
spetlr/delta/delta_handle.py
spetlr/deltaspec/DeltaDatabaseSpec.py
spetlr/deltaspec/DeltaTableSpec.py
spetlr/deltaspec/DeltaTableSpecBase.py
spetlr/deltaspec/DeltaTableSpecDifference.py
spetlr/deltaspec/__init__.py
spetlr/deltaspec/exceptions.py
spetlr/deltaspec/helpers.py
spetlr/eh/EventHubCapture.py
spetlr/eh/EventHubCaptureExtractor.py
spetlr/eh/EventHubJsonPublisher.py
spetlr/eh/EventHubStream.py
spetlr/eh/EventhubStreamConnectionStringEncrypt.py
spetlr/eh/PartitionSpec.py
spetlr/eh/__init__.py
spetlr/eh/eh_exceptions.py
spetlr/eh/eventhub_handle.py
spetlr/entry_points/__init__.py
spetlr/entry_points/generalized_task_entry_point.py
spetlr/entry_points/task_entry_point.py
spetlr/etl/__init__.py
spetlr/etl/extractor.py
spetlr/etl/loader.py
spetlr/etl/orchestrator.py
spetlr/etl/transformer.py
spetlr-16.4.6.dist-info/licenses/LICENSE
spetlr-16.4.6.dist-info/METADATA
spetlr-16.4.6.dist-info/WHEEL
spetlr-16.4.6.dist-info/entry_points.txt
spetlr-16.4.6.dist-info/top_level.txt
spetlr-16.4.6.dist-info/RECORD
