Metadata-Version: 2.4
Name: spetlr
Version: 16.4.6
Summary: A python ETL libRary (SPETLR) for Databricks powered by Apache SPark.
Home-page: https://github.com/spetlr-org/spetlr
Author: Spetlr.Org
Author-email: spetlr.org@gmail.com
Project-URL: Documentation, https://github.com/spetlr-org/spetlr
Project-URL: Bug Reports, https://github.com/spetlr-org/spetlr/issues
Project-URL: Source Code, https://github.com/spetlr-org/spetlr
Keywords: databricks,pyspark
Classifier: Development Status :: 2 - Pre-Alpha
Classifier: Intended Audience :: Developers
Classifier: Topic :: Software Development :: Build Tools
Classifier: Programming Language :: Python :: 3
Classifier: Programming Language :: Python :: 3.12
Classifier: Programming Language :: Python :: 3 :: Only
Classifier: License :: OSI Approved :: MIT License
Classifier: Operating System :: OS Independent
Requires-Python: >=3.12
License-File: LICENSE
Requires-Dist: pyyaml
Requires-Dist: sqlparse>=0.4.4
Requires-Dist: Deprecated
Requires-Dist: pyodbc
Requires-Dist: importlib-metadata
Requires-Dist: azure-cosmos
Requires-Dist: timezonefinder
Requires-Dist: more_itertools
Requires-Dist: pycountry
Requires-Dist: databricks-sdk
Requires-Dist: numpy
Requires-Dist: urllib3
Requires-Dist: msal
Requires-Dist: pandas
Requires-Dist: pycryptodome
Dynamic: license-file
